{
  "url": "https://www.99acres.com/1-bhk-bedroom-apartment-flat-for-sale-in-sector-26-vasi-navi-mumbai-415-sq-ft-spid-V85831450",
  "scrapedAt": "2026-05-04T06:05:48.376Z",
  "data": {
    "propertyTitle": "1BHK 1Bath Flat/Apartment for Sale in shiv kripa, Sector 26 Vashi, Navi Mumbai"
  },
  "validationError": {
    "name": "ZodError",
    "message": "[\n  {\n    \"expected\": \"string\",\n    \"code\": \"invalid_type\",\n    \"path\": [\n      \"propertyType\"\n    ],\n    \"message\": \"Invalid input: expected string, received undefined\"\n  },\n  {\n    \"expected\": \"string\",\n    \"code\": \"invalid_type\",\n    \"path\": [\n      \"bhkType\"\n    ],\n    \"message\": \"Invalid input: expected string, received undefined\"\n  },\n  {\n    \"expected\": \"string\",\n    \"code\": \"invalid_type\",\n    \"path\": [\n      \"projectType\"\n    ],\n    \"message\": \"Invalid input: expected string, received undefined\"\n  },\n  {\n    \"expected\": \"string\",\n    \"code\": \"invalid_type\",\n    \"path\": [\n      \"location\"\n    ],\n    \"message\": \"Invalid input: expected string, received undefined\"\n  },\n  {\n    \"expected\": \"string\",\n    \"code\": \"invalid_type\",\n    \"path\": [\n      \"address\"\n    ],\n    \"message\": \"Invalid input: expected string, received undefined\"\n  },\n  {\n    \"expected\": \"string\",\n    \"code\": \"invalid_type\",\n    \"path\": [\n      \"city\"\n    ],\n    \"message\": \"Invalid input: expected string, received undefined\"\n  },\n  {\n    \"expected\": \"array\",\n    \"code\": \"invalid_type\",\n    \"path\": [\n      \"nearbyLandmarks\"\n    ],\n    \"message\": \"Invalid input: expected array, received undefined\"\n  },\n  {\n    \"expected\": \"string\",\n    \"code\": \"invalid_type\",\n    \"path\": [\n      \"price\"\n    ],\n    \"message\": \"Invalid input: expected string, received undefined\"\n  },\n  {\n    \"expected\": \"string\",\n    \"code\": \"invalid_type\",\n    \"path\": [\n      \"pricePerSqft\"\n    ],\n    \"message\": \"Invalid input: expected string, received undefined\"\n  },\n  {\n    \"expected\": \"string\",\n    \"code\": \"invalid_type\",\n    \"path\": [\n      \"priceRange\"\n    ],\n    \"message\": \"Invalid input: expected string, received undefined\"\n  },\n  {\n    \"expected\": \"string\",\n    \"code\": \"invalid_type\",\n    \"path\": [\n      \"estimatedEMI\"\n    ],\n    \"message\": \"Invalid input: expected string, received undefined\"\n  },\n  {\n    \"expected\": \"boolean\",\n    \"code\": \"invalid_type\",\n    \"path\": [\n      \"negotiable\"\n    ],\n    \"message\": \"Invalid input: expected boolean, received undefined\"\n  },\n  {\n    \"expected\": \"string\",\n    \"code\": \"invalid_type\",\n    \"path\": [\n      \"bookingAmount\"\n    ],\n    \"message\": \"Invalid input: expected string, received undefined\"\n  },\n  {\n    \"expected\": \"string\",\n    \"code\": \"invalid_type\",\n    \"path\": [\n      \"maintenanceCharges\"\n    ],\n    \"message\": \"Invalid input: expected string, received undefined\"\n  },\n  {\n    \"expected\": \"string\",\n    \"code\": \"invalid_type\",\n    \"path\": [\n      \"area\"\n    ],\n    \"message\": \"Invalid input: expected string, received undefined\"\n  },\n  {\n    \"expected\": \"string\",\n    \"code\": \"invalid_type\",\n    \"path\": [\n      \"floorNo\"\n    ],\n    \"message\": \"Invalid input: expected string, received undefined\"\n  },\n  {\n    \"expected\": \"number\",\n    \"code\": \"invalid_type\",\n    \"path\": [\n      \"totalFloors\"\n    ],\n    \"message\": \"Invalid input: expected number, received undefined\"\n  },\n  {\n    \"expected\": \"string\",\n    \"code\": \"invalid_type\",\n    \"path\": [\n      \"furnishingStatus\"\n    ],\n    \"message\": \"Invalid input: expected string, received undefined\"\n  },\n  {\n    \"expected\": \"number\",\n    \"code\": \"invalid_type\",\n    \"path\": [\n      \"numberOfBathrooms\"\n    ],\n    \"message\": \"Invalid input: expected number, received undefined\"\n  },\n  {\n    \"expected\": \"number\",\n    \"code\": \"invalid_type\",\n    \"path\": [\n      \"numberOfBalconies\"\n    ],\n    \"message\": \"Invalid input: expected number, received undefined\"\n  },\n  {\n    \"expected\": \"string\",\n    \"code\": \"invalid_type\",\n    \"path\": [\n      \"facing\"\n    ],\n    \"message\": \"Invalid input: expected string, received undefined\"\n  },\n  {\n    \"expected\": \"string\",\n    \"code\": \"invalid_type\",\n    \"path\": [\n      \"overlooking\"\n    ],\n    \"message\": \"Invalid input: expected string, received undefined\"\n  },\n  {\n    \"expected\": \"string\",\n    \"code\": \"invalid_type\",\n    \"path\": [\n      \"carParking\"\n    ],\n    \"message\": \"Invalid input: expected string, received undefined\"\n  },\n  {\n    \"expected\": \"string\",\n    \"code\": \"invalid_type\",\n    \"path\": [\n      \"flooringType\"\n    ],\n    \"message\": \"Invalid input: expected string, received undefined\"\n  },\n  {\n    \"expected\": \"string\",\n    \"code\": \"invalid_type\",\n    \"path\": [\n      \"constructionStatus\"\n    ],\n    \"message\": \"Invalid input: expected string, received undefined\"\n  },\n  {\n    \"expected\": \"string\",\n    \"code\": \"invalid_type\",\n    \"path\": [\n      \"possessionDate\"\n    ],\n    \"message\": \"Invalid input: expected string, received undefined\"\n  },\n  {\n    \"expected\": \"string\",\n    \"code\": \"invalid_type\",\n    \"path\": [\n      \"postedDate\"\n    ],\n    \"message\": \"Invalid input: expected string, received undefined\"\n  },\n  {\n    \"expected\": \"string\",\n    \"code\": \"invalid_type\",\n    \"path\": [\n      \"ageOfBuilding\"\n    ],\n    \"message\": \"Invalid input: expected string, received undefined\"\n  },\n  {\n    \"expected\": \"string\",\n    \"code\": \"invalid_type\",\n    \"path\": [\n      \"launchDate\"\n    ],\n    \"message\": \"Invalid input: expected string, received undefined\"\n  },\n  {\n    \"expected\": \"string\",\n    \"code\": \"invalid_type\",\n    \"path\": [\n      \"projectName\"\n    ],\n    \"message\": \"Invalid input: expected string, received undefined\"\n  },\n  {\n    \"expected\": \"string\",\n    \"code\": \"invalid_type\",\n    \"path\": [\n      \"developerName\"\n    ],\n    \"message\": \"Invalid input: expected string, received undefined\"\n  },\n  {\n    \"expected\": \"number\",\n    \"code\": \"invalid_type\",\n    \"path\": [\n      \"totalUnits\"\n    ],\n    \"message\": \"Invalid input: expected number, received undefined\"\n  },\n  {\n    \"expected\": \"string\",\n    \"code\": \"invalid_type\",\n    \"path\": [\n      \"projectSize\"\n    ],\n    \"message\": \"Invalid input: expected string, received undefined\"\n  },\n  {\n    \"expected\": \"string\",\n    \"code\": \"invalid_type\",\n    \"path\": [\n      \"popularityRank\"\n    ],\n    \"message\": \"Invalid input: expected string, received undefined\"\n  },\n  {\n    \"expected\": \"boolean\",\n    \"code\": \"invalid_type\",\n    \"path\": [\n      \"reraApproved\"\n    ],\n    \"message\": \"Invalid input: expected boolean, received undefined\"\n  },\n  {\n    \"expected\": \"string\",\n    \"code\": \"invalid_type\",\n    \"path\": [\n      \"reraNumber\"\n    ],\n    \"message\": \"Invalid input: expected string, received undefined\"\n  },\n  {\n    \"expected\": \"boolean\",\n    \"code\": \"invalid_type\",\n    \"path\": [\n      \"verifiedTag\"\n    ],\n    \"message\": \"Invalid input: expected boolean, received undefined\"\n  },\n  {\n    \"expected\": \"boolean\",\n    \"code\": \"invalid_type\",\n    \"path\": [\n      \"loanVerified\"\n    ],\n    \"message\": \"Invalid input: expected boolean, received undefined\"\n  },\n  {\n    \"expected\": \"string\",\n    \"code\": \"invalid_type\",\n    \"path\": [\n      \"ownershipType\"\n    ],\n    \"message\": \"Invalid input: expected string, received undefined\"\n  },\n  {\n    \"expected\": \"boolean\",\n    \"code\": \"invalid_type\",\n    \"path\": [\n      \"legalCertificatesAvailable\"\n    ],\n    \"message\": \"Invalid input: expected boolean, received undefined\"\n  },\n  {\n    \"expected\": \"boolean\",\n    \"code\": \"invalid_type\",\n    \"path\": [\n      \"brochureDownload\"\n    ],\n    \"message\": \"Invalid input: expected boolean, received undefined\"\n  },\n  {\n    \"expected\": \"array\",\n    \"code\": \"invalid_type\",\n    \"path\": [\n      \"amenities\"\n    ],\n    \"message\": \"Invalid input: expected array, received undefined\"\n  },\n  {\n    \"expected\": \"string\",\n    \"code\": \"invalid_type\",\n    \"path\": [\n      \"sellerType\"\n    ],\n    \"message\": \"Invalid input: expected string, received undefined\"\n  },\n  {\n    \"expected\": \"string\",\n    \"code\": \"invalid_type\",\n    \"path\": [\n      \"agentName\"\n    ],\n    \"message\": \"Invalid input: expected string, received undefined\"\n  },\n  {\n    \"expected\": \"string\",\n    \"code\": \"invalid_type\",\n    \"path\": [\n      \"contactDetails\"\n    ],\n    \"message\": \"Invalid input: expected string, received undefined\"\n  },\n  {\n    \"expected\": \"string\",\n    \"code\": \"invalid_type\",\n    \"path\": [\n      \"responseRate\"\n    ],\n    \"message\": \"Invalid input: expected string, received undefined\"\n  },\n  {\n    \"expected\": \"string\",\n    \"code\": \"invalid_type\",\n    \"path\": [\n      \"buyersServed\"\n    ],\n    \"message\": \"Invalid input: expected string, received undefined\"\n  },\n  {\n    \"expected\": \"number\",\n    \"code\": \"invalid_type\",\n    \"path\": [\n      \"uniqueViews\"\n    ],\n    \"message\": \"Invalid input: expected number, received undefined\"\n  },\n  {\n    \"expected\": \"number\",\n    \"code\": \"invalid_type\",\n    \"path\": [\n      \"shortlists\"\n    ],\n    \"message\": \"Invalid input: expected number, received undefined\"\n  },\n  {\n    \"expected\": \"string\",\n    \"code\": \"invalid_type\",\n    \"path\": [\n      \"carpetArea\"\n    ],\n    \"message\": \"Invalid input: expected string, received undefined\"\n  },\n  {\n    \"expected\": \"number\",\n    \"code\": \"invalid_type\",\n    \"path\": [\n      \"contactsMade\"\n    ],\n    \"message\": \"Invalid input: expected number, received undefined\"\n  },\n  {\n    \"expected\": \"number\",\n    \"code\": \"invalid_type\",\n    \"path\": [\n      \"livabilityScore\"\n    ],\n    \"message\": \"Invalid input: expected number, received undefined\"\n  },\n  {\n    \"expected\": \"number\",\n    \"code\": \"invalid_type\",\n    \"path\": [\n      \"transitScore\"\n    ],\n    \"message\": \"Invalid input: expected number, received undefined\"\n  },\n  {\n    \"expected\": \"number\",\n    \"code\": \"invalid_type\",\n    \"path\": [\n      \"safetyScore\"\n    ],\n    \"message\": \"Invalid input: expected number, received undefined\"\n  },\n  {\n    \"expected\": \"number\",\n    \"code\": \"invalid_type\",\n    \"path\": [\n      \"numberOfPhotos\"\n    ],\n    \"message\": \"Invalid input: expected number, received undefined\"\n  },\n  {\n    \"expected\": \"boolean\",\n    \"code\": \"invalid_type\",\n    \"path\": [\n      \"videoTourAvailable\"\n    ],\n    \"message\": \"Invalid input: expected boolean, received undefined\"\n  },\n  {\n    \"expected\": \"string\",\n    \"code\": \"invalid_type\",\n    \"path\": [\n      \"marketPrice\"\n    ],\n    \"message\": \"Invalid input: expected string, received undefined\"\n  },\n  {\n    \"expected\": \"string\",\n    \"code\": \"invalid_type\",\n    \"path\": [\n      \"ownerName\"\n    ],\n    \"message\": \"Invalid input: expected string, received undefined\"\n  }\n]"
  }
}